rtl/memory/rom_beta.v
// =============================================================================
// Módulo: rom_beta.v
// Função: Armazena os pesos β da camada de saída da ELM.
//         10 classes × 128 neurônios ocultos = 1.280 pesos de 16 bits (Q4.12).
// Tipo: ROM síncrona de porta única — sem escrita em runtime.
//
// Endereço composto (11 bits):
//   addr = {class_idx[3:0], hidden_idx[6:0]}
//
//   Cálculo: addr = class_idx * 128 + hidden_idx
//   β[0][0]   → {4'd0, 7'd0}   = 0
//   β[0][127] → {4'd0, 7'd127} = 127
//   β[1][0]   → {4'd1, 7'd0}   = 128
//   β[9][127] → {4'd9, 7'd127} = 1279  (endereço máximo)
//
// Nota sobre profundidade:
//   2^11 = 2048, mas apenas 1280 posições são usadas.
//   O endereço máximo válido é 1279 < 2047, portanto sem out-of-bounds.
//   mem é declarado com 1280 entradas para ser preciso e poupar recursos.
//
// Arquivo de inicialização: beta.hex
//   Formato: $readmemh — um valor hex por linha, sem cabeçalho.
//   Gerado por: scripts/gen_hex.py a partir de beta_q.txt
//
// Referência: test_spec_memories.md — Módulo 4 (TC-BETA-01 a TC-BETA-04)
// =============================================================================

module rom_beta (
    input             clk,
    input      [10:0] addr,       // {class_idx[3:0], hidden_idx[6:0]}
    output reg [15:0] data_out    // peso β[classe][neurônio] em Q4.12
);

    // -------------------------------------------------------------------------
    // Declaração da memória
    //
    // [15:0]   → cada posição guarda 16 bits (peso β em Q4.12)
    // [1279:0] → 1280 posições = 10 classes × 128 neurônios
    // -------------------------------------------------------------------------
    reg [15:0] mem [1279:0];

    // -------------------------------------------------------------------------
    // Inicialização com os pesos β reais (Q4.12)
    //
    // beta.hex: 1280 linhas.
    //   linha 0    → β[0][0]   (classe 0, neurônio oculto 0)
    //   linha 127  → β[0][127]
    //   linha 128  → β[1][0]
    //   linha 1279 → β[9][127]
    // -------------------------------------------------------------------------
    initial $readmemh("beta_q.hex", mem);

    // -------------------------------------------------------------------------
    // Lógica de leitura — bloco síncrono, latência de 1 ciclo.
    // -------------------------------------------------------------------------
    always @(posedge clk) begin
        data_out <= mem[addr];
    end

endmodule

rtl/tb/tb_rom_beta.v
// =============================================================================
// Testbench: tb_rom_beta.v
// Módulo sob teste: rom_beta.v
// Referência: test_spec_memories.md — Módulo 4 (TC-BETA-01 a TC-BETA-04)
//
// Como executar (Icarus Verilog):
//   iverilog -o tb_rom_beta tb_rom_beta.v rom_beta.v && vvp tb_rom_beta
//
// REQUISITO: beta.hex deve estar no mesmo diretório que os arquivos .v
//
// Valores de referência (extraídos de beta_q.txt em Q4.12):
//   β[0][0]   = beta[0]    = -131 → 0xFF7D
//   β[9][127] = beta[1279] =   11 → 0x000B
//   β[1][0]   = beta[128]  =   13 → 0x000D  (usado no TC-BETA-03)
// =============================================================================

`timescale 1ns/1ps

module tb_rom_beta;

    // -------------------------------------------------------------------------
    // Sinais de interface com o DUT
    // -------------------------------------------------------------------------
    reg         clk;
    reg  [10:0] addr;
    wire [15:0] data_out;

    // -------------------------------------------------------------------------
    // Contadores de PASS / FAIL
    // -------------------------------------------------------------------------
    integer pass_count;
    integer fail_count;

    // -------------------------------------------------------------------------
    // Valores esperados — pesos reais em Q4.12 (fonte: beta_q.txt)
    //
    //   β[0][0]   = beta[0]    = -131 → 0xFF7D
    //   β[9][127] = beta[1279] = 11   → 0x000B
    //   β[1][0]   = beta[128]  = 13   → 0x000D
    //
    // Verificação:
    //   -131 & 0xFFFF = 65536 - 131 = 65405 = 0xFF7D ✓
    // -------------------------------------------------------------------------
    localparam BETA_0_0   = 16'hFF7D;   // β[0][0]   addr=0
    localparam BETA_9_127 = 16'h000B;   // β[9][127] addr=1279
    localparam BETA_1_0   = 16'h000D;   // β[1][0]   addr=128 (para TC-BETA-03)

    // -------------------------------------------------------------------------
    // Array para varredura (TC-BETA-04)
    // -------------------------------------------------------------------------
    reg [15:0] expected [1279:0];

    // -------------------------------------------------------------------------
    // Instância do DUT
    // -------------------------------------------------------------------------
    rom_beta dut (
        .clk      (clk),
        .addr     (addr),
        .data_out (data_out)
    );

    // -------------------------------------------------------------------------
    // Geração de clock: período de 10 ns (100 MHz)
    // -------------------------------------------------------------------------
    initial clk = 0;
    always #5 clk = ~clk;

    // -------------------------------------------------------------------------
    // Task auxiliar
    // -------------------------------------------------------------------------
    task check;
        input [63:0]  tc_num;
        input [15:0]  got;
        input [15:0]  exp;
        begin
            if (got === exp) begin
                $display("  PASS  TC-BETA-%0d | got=0x%04X  exp=0x%04X", tc_num, got, exp);
                pass_count = pass_count + 1;
            end else begin
                $display("  FAIL  TC-BETA-%0d | got=0x%04X  exp=0x%04X  <---", tc_num, got, exp);
                fail_count = fail_count + 1;
            end
        end
    endtask

    // =========================================================================
    // Sequência principal de testes
    // =========================================================================
    integer c, h;
    reg test_passed;

    initial begin
        pass_count = 0;
        fail_count = 0;
        addr = 0;

        $readmemh("beta.hex", expected);

        #3;

        $display("=============================================================");
        $display(" tb_rom_beta — Iniciando testes (TC-BETA-01 a TC-BETA-04)");
        $display(" Pesos reais Q4.12 carregados de beta.hex");
        $display("=============================================================");

        // ---------------------------------------------------------------------
        // TC-BETA-01 — Leitura de β[0][0]
        //
        // β[0][0] = -131 → 0xFF7D
        // Endereço: {4'd0, 7'd0} = 11'd0
        // ---------------------------------------------------------------------
        $display("\n-- TC-BETA-01: leitura beta[0][0] (esperado 0xFF7D = -131) --");
        @(posedge clk); #1;
        addr = {4'd0, 7'd0};

        @(posedge clk); #1;
        check(1, data_out, BETA_0_0);

        // ---------------------------------------------------------------------
        // TC-BETA-02 — Leitura de β[9][127] (endereço máximo = 1279)
        //
        // β[9][127] = 11 → 0x000B
        // Endereço: {4'd9, 7'd127} = 11'd1279
        // ---------------------------------------------------------------------
        $display("\n-- TC-BETA-02: leitura beta[9][127] (addr maximo, esperado 0x000B = 11) --");
        @(posedge clk); #1;
        addr = {4'd9, 7'd127};

        @(posedge clk); #1;
        check(2, data_out, BETA_9_127);

        // ---------------------------------------------------------------------
        // TC-BETA-03 — Independência entre classes: β[0][0] ≠ β[1][0]
        //
        // β[0][0] = -131 (0xFF7D)   addr = 0
        // β[1][0] =   13 (0x000D)   addr = 128
        // Verifica que class_idx distingue corretamente as linhas de β.
        // ---------------------------------------------------------------------
        $display("\n-- TC-BETA-03: independencia entre classes --");

        // Lê β[0][0]
        @(posedge clk); #1;
        addr = {4'd0, 7'd0};
        @(posedge clk); #1;
        // data_out = β[0][0] = 0xFF7D

        // Lê β[1][0]
        @(posedge clk); #1;
        addr = {4'd1, 7'd0};
        @(posedge clk); #1;
        // data_out = β[1][0] = 0x000D

        // Verifica que β[1][0] ≠ β[0][0]
        if (data_out !== BETA_0_0) begin
            $display("  PASS  TC-BETA-03 | beta[1][0]=0x%04X != beta[0][0]=0x%04X: classes independentes",
                     data_out, BETA_0_0);
            pass_count = pass_count + 1;
        end else begin
            $display("  FAIL  TC-BETA-03 | beta[0][0] == beta[1][0]: class_idx incorreto?  <---");
            fail_count = fail_count + 1;
        end

        // Verifica também o valor exato de β[1][0]
        check(3, data_out, BETA_1_0);

        // ---------------------------------------------------------------------
        // TC-BETA-04 — Varredura por amostragem: 3 classes × 3 neurônios
        //
        // Compara com expected[] carregado do beta.hex.
        // Posições verificadas para cada classe c em {0, 4, 9}:
        //   β[c][0], β[c][63], β[c][127]
        // ---------------------------------------------------------------------
        $display("\n-- TC-BETA-04: varredura por amostragem (3 classes x 3 neuronios) --");
        test_passed = 1;

        begin : varredura
            integer classe;
            integer neuron;
            integer expected_addr;

            for (classe = 0; classe <= 9; classe = classe + 4) begin
                if (classe == 8) classe = 9;

                for (neuron = 0; neuron <= 127; neuron = neuron + 63) begin
                    if (neuron == 126) neuron = 127;

                    expected_addr = classe * 128 + neuron;

                    @(posedge clk); #1;
                    addr = {classe[3:0], neuron[6:0]};

                    @(posedge clk); #1;

                    if (data_out !== expected[expected_addr]) begin
                        $display("  FAIL  TC-BETA-04 | beta[%0d][%0d] got=0x%04X exp=0x%04X  <---",
                                 classe, neuron, data_out, expected[expected_addr]);
                        fail_count = fail_count + 1;
                        test_passed = 0;
                    end
                end
            end
        end

        if (test_passed) begin
            $display("  PASS  TC-BETA-04 | 9/9 posicoes amostradas corretas (pesos reais Q4.12)");
            pass_count = pass_count + 1;
        end

        // =====================================================================
        // Relatório final
        // =====================================================================
        $display("\n=============================================================");
        $display(" RESULTADO FINAL");
        $display("   PASS : %0d", pass_count);
        $display("   FAIL : %0d", fail_count);
        $display("   TOTAL: %0d", pass_count + fail_count);
        if (fail_count == 0)
            $display(" >> TODOS OS TESTES PASSARAM <<");
        else
            $display(" >> ATENCAO: %0d TESTE(S) FALHARAM <<", fail_count);
        $display("=============================================================");

        $finish;
    end

    // -------------------------------------------------------------------------
    // Dump de waveform para GTKWave
    // -------------------------------------------------------------------------
    initial begin
        $dumpfile("tb_rom_beta.vcd");
        $dumpvars(0, tb_rom_beta);
    end

endmodule

rtl/memory/tb_rom_beta.vcd
$date
	Mon Mar 23 16:04:13 2026
$end
$version
	Icarus Verilog
$end
$timescale
	1ps
$end
$scope module tb_rom_beta $end
$var wire 16 ! data_out [15:0] $end
$var reg 11 " addr [10:0] $end
$var reg 1 # clk $end
$var reg 1 $ test_passed $end
$var integer 32 % fail_count [31:0] $end
$var integer 32 & pass_count [31:0] $end
$scope module dut $end
$var wire 11 ' addr [10:0] $end
$var wire 1 # clk $end
$var reg 16 ( data_out [15:0] $end
$upscope $end
$scope begin varredura $end
$var integer 32 ) classe [31:0] $end
$var integer 32 * expected_addr [31:0] $end
$var integer 32 + neuron [31:0] $end
$upscope $end
$scope task check $end
$var reg 16 , exp [15:0] $end
$var reg 16 - got [15:0] $end
$var reg 64 . tc_num [63:0] $end
$upscope $end
$upscope $end
$enddefinitions $end
$comment Show the parameter values. $end
$dumpall
$end
#0
$dumpvars
bx .
bx -
bx ,
bx +
bx *
bx )
bx (
b0 '
b0 &
b0 %
x$
0#
b0 "
bx !
$end
#5000
b1111111111001110 !
b1111111111001110 (
1#
#10000
0#
#15000
1#
#16000
b1 &
b1111111111001110 ,
b1111111111001110 -
b1 .
#20000
0#
#25000
1#
#26000
b10011111111 "
b10011111111 '
#30000
0#
#35000
b1000 !
b1000 (
1#
#36000
b10 &
b1000 ,
b1000 -
b10 .
#40000
0#
#45000
1#
#46000
b0 "
b0 '
#50000
0#
#55000
b1111111111001110 !
b1111111111001110 (
1#
#60000
0#
#65000
1#
#66000
b1 "
b1 '
#70000
0#
#75000
b110010 !
b110010 (
1#
#76000
b0 *
b0 )
b0 +
1$
b110010 ,
b110010 -
b11 .
b100 &
#80000
0#
#85000
1#
#86000
b0 "
b0 '
#90000
0#
#95000
b1111111111001110 !
b1111111111001110 (
1#
#96000
b100 *
b100 )
#100000
0#
#105000
1#
#106000
b100 "
b100 '
#110000
0#
#115000
b0 !
b0 (
1#
#116000
b1001 *
b1001 )
#120000
0#
#125000
1#
#126000
b1001 "
b1001 '
#130000
0#
#135000
b1111111111101011 !
b1111111111101011 (
1#
#136000
b1001110110 *
b111111 +
b0 )
#140000
0#
#145000
1#
#146000
b1001110110 "
b1001110110 '
#150000
0#
#155000
b1111111111111111 !
b1111111111111111 (
1#
#156000
b1001111010 *
b100 )
#160000
0#
#165000
1#
#166000
b1001111010 "
b1001111010 '
#170000
0#
#175000
b1111111110101100 !
b1111111110101100 (
1#
#176000
b1001111111 *
b1001 )
#180000
0#
#185000
1#
#186000
b1001111111 "
b1001111111 '
#190000
0#
#195000
b1111111110101011 !
b1111111110101011 (
1#
#196000
b10011110110 *
b1111111 +
b0 )
#200000
0#
#205000
1#
#206000
b10011110110 "
b10011110110 '
#210000
0#
#215000
b1111111111101010 !
b1111111111101010 (
1#
#216000
b10011111010 *
b100 )
#220000
0#
#225000
1#
#226000
b10011111010 "
b10011111010 '
#230000
0#
#235000
b1111111111101001 !
b1111111111101001 (
1#
#236000
b10011111111 *
b1001 )
#240000
0#
#245000
1#
#246000
b10011111111 "
b10011111111 '
#250000
0#
#255000
b1000 !
b1000 (
1#
#256000
b101 &
b10111110 +
b1101 )
